<?xml version="1.0" encoding="UTF-8"?>
<index>
  <record uri="http://syriaca.org/manuscript/437">
    <part uri="http://syriaca.org/manuscript/438">
      <update timeStamp="2021-12-07T14:22:12.223-05:00">
        <oldId>a1</oldId>
        <newId>p1a1</newId>
      </update>
      <update timeStamp="2021-12-07T14:22:12.223-05:00">
        <oldId>b1</oldId>
        <newId>p1b1</newId>
      </update>
      <update timeStamp="2021-12-07T14:22:12.223-05:00">
        <oldId>handNote1</oldId>
        <newId>p1handNote1</newId>
      </update>
    </part>
    <part uri="http://syriaca.org/manuscript/1479">
      <update timeStamp="2021-12-07T14:22:12.223-05:00">
        <oldId/>
        <newId>p2a1</newId>
      </update>
      <update timeStamp="2021-12-07T14:22:12.223-05:00">
        <oldId/>
        <newId>p2b1</newId>
      </update>
      <update timeStamp="2021-12-07T14:22:12.223-05:00">
        <oldId/>
        <newId>p2a2</newId>
      </update>
      <update timeStamp="2021-12-07T14:22:12.223-05:00">
        <oldId/>
        <newId>p2b2</newId>
      </update>
      <update timeStamp="2021-12-07T14:22:12.223-05:00">
        <oldId>handNote1</oldId>
        <newId>p2handNote1</newId>
      </update>
    </part>
    <part uri="http://syriaca.org/manuscript/1484">
      <update timeStamp="2021-12-07T14:22:12.223-05:00">
        <oldId/>
        <newId>p3a1</newId>
      </update>
      <update timeStamp="2021-12-07T14:22:12.223-05:00">
        <oldId>handNote1</oldId>
        <newId>p3handNote1</newId>
      </update>
    </part>
    <part uri="http://syriaca.org/manuscript/1485">
      <update timeStamp="2021-12-07T14:22:12.223-05:00">
        <oldId/>
        <newId>p4a1</newId>
      </update>
      <update timeStamp="2021-12-07T14:22:12.223-05:00">
        <oldId>handNote2</oldId>
        <newId>p4handNote1</newId>
      </update>
    </part>
    <part uri="http://syriaca.org/manuscript/1486">
      <update timeStamp="2021-12-07T14:22:12.223-05:00">
        <oldId/>
        <newId>p5a1</newId>
      </update>
      <update timeStamp="2021-12-07T14:22:12.223-05:00">
        <oldId>handNote3</oldId>
        <newId>p5handNote1</newId>
      </update>
    </part>
    <part uri="http://syriaca.org/manuscript/439">
      <update timeStamp="2021-12-07T14:22:12.223-05:00">
        <oldId>a1</oldId>
        <newId>p6a1</newId>
      </update>
      <update timeStamp="2021-12-07T14:22:12.223-05:00">
        <oldId>handNote1</oldId>
        <newId>p6handNote1</newId>
      </update>
    </part>
    <part uri="http://syriaca.org/manuscript/1480">
      <update timeStamp="2021-12-07T14:22:12.223-05:00">
        <oldId>a1</oldId>
        <newId>p7a1</newId>
      </update>
      <update timeStamp="2021-12-07T14:22:12.223-05:00">
        <oldId>handNote1</oldId>
        <newId>p7handNote1</newId>
      </update>
    </part>
    <part uri="http://syriaca.org/manuscript/440">
      <update timeStamp="2021-12-07T14:22:12.223-05:00">
        <oldId>a1</oldId>
        <newId>p8a1</newId>
      </update>
      <update timeStamp="2021-12-07T14:22:12.223-05:00">
        <oldId>a2</oldId>
        <newId>p8a2</newId>
      </update>
      <update timeStamp="2021-12-07T14:22:12.223-05:00">
        <oldId/>
        <newId>p8b1</newId>
      </update>
      <update timeStamp="2021-12-07T14:22:12.223-05:00">
        <oldId>a3</oldId>
        <newId>p8a3</newId>
      </update>
      <update timeStamp="2021-12-07T14:22:12.223-05:00">
        <oldId>a4</oldId>
        <newId>p8a4</newId>
      </update>
      <update timeStamp="2021-12-07T14:22:12.223-05:00">
        <oldId>a5</oldId>
        <newId>p8a5</newId>
      </update>
      <update timeStamp="2021-12-07T14:22:12.223-05:00">
        <oldId>handNote1</oldId>
        <newId>p8handNote1</newId>
      </update>
    </part>
    <part uri="http://syriaca.org/manuscript/1481">
      <update timeStamp="2021-12-07T14:22:12.223-05:00">
        <oldId/>
        <newId>p9a1</newId>
      </update>
      <update timeStamp="2021-12-07T14:22:12.223-05:00">
        <oldId/>
        <newId>p9a2</newId>
      </update>
      <update timeStamp="2021-12-07T14:22:12.223-05:00">
        <oldId/>
        <newId>p9a3</newId>
      </update>
      <update timeStamp="2021-12-07T14:22:12.223-05:00">
        <oldId>handNote1</oldId>
        <newId>p9handNote1</newId>
      </update>
    </part>
    <part uri="http://syriaca.org/manuscript/441">
      <update timeStamp="2021-12-07T14:22:12.223-05:00">
        <oldId>a1</oldId>
        <newId>p10a1</newId>
      </update>
      <update timeStamp="2021-12-07T14:22:12.223-05:00">
        <oldId>handNote1</oldId>
        <newId>p10handNote1</newId>
      </update>
    </part>
    <part uri="http://syriaca.org/manuscript/1185">
      <update timeStamp="2021-12-07T14:22:12.223-05:00">
        <oldId>a2</oldId>
        <newId>p11a1</newId>
      </update>
      <update timeStamp="2021-12-07T14:22:12.223-05:00">
        <oldId>handNote1</oldId>
        <newId>p11handNote1</newId>
      </update>
    </part>
    <part uri="http://syriaca.org/manuscript/442">
      <update timeStamp="2021-12-07T14:22:12.223-05:00">
        <oldId>a1</oldId>
        <newId>p12a1</newId>
      </update>
      <update timeStamp="2021-12-07T14:22:12.223-05:00">
        <oldId>handNote1</oldId>
        <newId>p12handNote1</newId>
      </update>
    </part>
    <part uri="http://syriaca.org/manuscript/443">
      <update timeStamp="2021-12-07T14:22:12.223-05:00">
        <oldId>a2</oldId>
        <newId>p13a1</newId>
      </update>
      <update timeStamp="2021-12-07T14:22:12.223-05:00">
        <oldId/>
        <newId>p13b1</newId>
      </update>
      <update timeStamp="2021-12-07T14:22:12.223-05:00">
        <oldId/>
        <newId>p13b2</newId>
      </update>
      <update timeStamp="2021-12-07T14:22:12.223-05:00">
        <oldId>handNote1</oldId>
        <newId>p13handNote1</newId>
      </update>
    </part>
    <part uri="http://syriaca.org/manuscript/1482">
      <update timeStamp="2021-12-07T14:22:12.223-05:00">
        <oldId>a1</oldId>
        <newId>p14a1</newId>
      </update>
      <update timeStamp="2021-12-07T14:22:12.223-05:00">
        <oldId>handNote1</oldId>
        <newId>p14handNote1</newId>
      </update>
    </part>
    <part uri="http://syriaca.org/manuscript/444">
      <update timeStamp="2021-12-07T14:22:12.223-05:00">
        <oldId>a1</oldId>
        <newId>p15a1</newId>
      </update>
      <update timeStamp="2021-12-07T14:22:12.223-05:00">
        <oldId>handNote1</oldId>
        <newId>p15handNote1</newId>
      </update>
      <update timeStamp="2021-12-07T14:22:12.223-05:00">
        <oldId>handNote2</oldId>
        <newId>p15handNote2</newId>
      </update>
      <update timeStamp="2021-12-07T14:22:12.223-05:00">
        <oldId>handNote3</oldId>
        <newId>p15handNote3</newId>
      </update>
      <update timeStamp="2021-12-07T14:22:12.223-05:00">
        <oldId/>
        <newId>p15addition1</newId>
      </update>
      <update timeStamp="2021-12-07T14:22:12.223-05:00">
        <oldId/>
        <newId>p15addition2</newId>
      </update>
    </part>
  </record>
</index>