<?xml version="1.0" encoding="UTF-8"?>
<index>
  <record uri="http://syriaca.org/manuscript/611">
    <part uri="http://syriaca.org/manuscript/612">
      <update timeStamp="2021-12-07T15:00:06.041-05:00">
        <oldId>a1</oldId>
        <newId>p1a1</newId>
      </update>
      <update timeStamp="2021-12-07T15:00:06.041-05:00">
        <oldId>a2</oldId>
        <newId>p1a2</newId>
      </update>
      <update timeStamp="2021-12-07T15:00:06.041-05:00">
        <oldId>a3</oldId>
        <newId>p1a3</newId>
      </update>
      <update timeStamp="2021-12-07T15:00:06.041-05:00">
        <oldId>a4</oldId>
        <newId>p1a4</newId>
      </update>
      <update timeStamp="2021-12-07T15:00:06.041-05:00">
        <oldId>a5</oldId>
        <newId>p1a5</newId>
      </update>
      <update timeStamp="2021-12-07T15:00:06.041-05:00">
        <oldId>a6</oldId>
        <newId>p1a6</newId>
      </update>
      <update timeStamp="2021-12-07T15:00:06.041-05:00">
        <oldId>a7</oldId>
        <newId>p1a7</newId>
      </update>
      <update timeStamp="2021-12-07T15:00:06.041-05:00">
        <oldId>a8</oldId>
        <newId>p1a8</newId>
      </update>
      <update timeStamp="2021-12-07T15:00:06.041-05:00">
        <oldId>handNote1</oldId>
        <newId>p1handNote1</newId>
      </update>
    </part>
    <part uri="http://syriaca.org/manuscript/613">
      <update timeStamp="2021-12-07T15:00:06.041-05:00">
        <oldId>a1</oldId>
        <newId>p2a1</newId>
      </update>
      <update timeStamp="2021-12-07T15:00:06.041-05:00">
        <oldId>a2</oldId>
        <newId>p2a2</newId>
      </update>
      <update timeStamp="2021-12-07T15:00:06.041-05:00">
        <oldId>handNote1</oldId>
        <newId>p2handNote1</newId>
      </update>
      <update timeStamp="2021-12-07T15:00:06.041-05:00">
        <oldId>handNote2</oldId>
        <newId>p2handNote2</newId>
      </update>
    </part>
  </record>
</index>